icmpx/__init__.py
icmpx/__main__.py
icmpx/_client.py
icmpx/_exceptions.py
icmpx/_models.py
icmpx/demo.py
icmpx/style.tcss
icmpx-0.1.6.dist-info/licenses/LICENSE
icmpx-0.1.6.dist-info/METADATA
icmpx-0.1.6.dist-info/WHEEL
icmpx-0.1.6.dist-info/entry_points.txt
icmpx-0.1.6.dist-info/top_level.txt
icmpx-0.1.6.dist-info/RECORD
