Metadata-Version: 2.4
Name: icmpx
Version: 0.1.6
Summary: A simple ICMP library for Python
Author: oornnery
License-Expression: MIT
Project-URL: Changelog, https://github.com/oornnery/icmpx/blob/main/CHANGELOG.md
Project-URL: Source, https://github.com/oornnery/icmpx
Project-URL: Tracker, https://github.com/oornnery/icmpx/issues
Keywords: icmp,ping,traceroute,networking,asyncio,textual,rich
Classifier: Programming Language :: Python :: 3 :: Only
Classifier: Programming Language :: Python :: 3.11
Classifier: Programming Language :: Python :: 3.12
Classifier: Programming Language :: Python :: 3.13
Classifier: Programming Language :: Python :: 3.14
Classifier: Operating System :: OS Independent
Classifier: Topic :: System :: Networking
Classifier: Operating System :: POSIX :: Linux
Requires-Python: >=3.11
License-File: LICENSE
Requires-Dist: rich>=14.2.0
Requires-Dist: textual>=6.2.1
Dynamic: license-file
